setup.cfg
setup.py
skyb/__init__.py
skyb.egg-info/PKG-INFO
skyb.egg-info/SOURCES.txt
skyb.egg-info/dependency_links.txt
skyb.egg-info/entry_points.txt
skyb.egg-info/top_level.txt
skyb/conf/__init__.py
skyb/conf/conf_loader.py
skyb/model/__init__.py
skyb/quick/__init__.py
skyb/quick/flyway/__init__.py
skyb/quick/tornado/__init__.py
skyb/test/__init__.py
skyb/test/test.py
skyb/utils/__init__.py