Metadata-Version: 1.1
Name: skyb
Version: 0.1.6
Summary: skypiea base
Home-page: https://github.com/woshifyz/skyb
Author: woshifyz
Author-email: monkey.d.pandora@gmail.com
License: MIT
Download-URL: https://github.com/woshifyz/skyb/tarball/0.1.6
Keywords: skypiea,base
Platform: UNKNOWN
